README.md
setup.cfg
setup.py
UnitSkuMasterPyforest/__init__.py
UnitSkuMasterPyforest/_importable.py
UnitSkuMasterPyforest/_imports.py
UnitSkuMasterPyforest/auto_import.py
UnitSkuMasterPyforest/user_specific_imports.py
UnitSkuMasterPyforest.egg-info/PKG-INFO
UnitSkuMasterPyforest.egg-info/SOURCES.txt
UnitSkuMasterPyforest.egg-info/dependency_links.txt
UnitSkuMasterPyforest.egg-info/top_level.txt